recurrent/__init__.py
recurrent/constants.py
recurrent/event_parser.py
recurrent/test.py
recurrent-0.3.0.dist-info/LICENSE
recurrent-0.3.0.dist-info/METADATA
recurrent-0.3.0.dist-info/WHEEL
recurrent-0.3.0.dist-info/top_level.txt
recurrent-0.3.0.dist-info/RECORD
