Metadata-Version: 2.1
Name: recurrent
Version: 0.3.0
Summary: Natural language parsing of recurring events
Home-page: http://github.com/kvh/recurrent
Author: Ken Van Haren
Author-email: kvh@science.io
License: BSD
Keywords: calendar recurring date event NLP
Platform: UNKNOWN
Classifier: Natural Language :: English
Classifier: Topic :: Text Processing :: Linguistic
Classifier: License :: OSI Approved :: BSD License
Requires-Dist: parsedatetime
